pame
