Metadata-Version: 1.1
Name: PAME
Version: 0.3.2
Summary: GUI for modeling nanoparticles on optical fiber with mixing/shell-filling models
Home-page: UNKNOWN
Author: Adam Hughes
Author-email: hughesadam87@gmail.com
License: LICENSE.txt
Download-URL: https://github.com/hugadams/fibersim
Platform: UNKNOWN
Classifier: Development Status :: 3 - Alpha
Classifier: Environment :: Console
Classifier: Intended Audience :: Science/Research
Classifier: Intended Audience :: Developers
Classifier: Natural Language :: English
Classifier: Programming Language :: Python :: 2
Classifier: Topic :: Scientific/Engineering :: Visualization
Classifier: Topic :: Scientific/Engineering :: Chemistry
Classifier: Topic :: Scientific/Engineering :: Physics
Classifier: Topic :: Scientific/Engineering :: Medical Science Apps.
